LICENSE
README.md
setup.py
request_id_middleware/__init__.py
request_id_middleware/middleware.py
request_id_middleware.egg-info/PKG-INFO
request_id_middleware.egg-info/SOURCES.txt
request_id_middleware.egg-info/dependency_links.txt
request_id_middleware.egg-info/requires.txt
request_id_middleware.egg-info/top_level.txt