Metadata-Version: 2.1
Name: request-id-middleware
Version: 0.1.0
Summary: Middleware for setting X-Request-Id header in Sentry scope
Home-page: https://github.com/Wafi-inc/request-id-middleware
Author: Oluwatosin Olasupo
Author-email: tosin@wafi.cash
Classifier: Programming Language :: Python :: 3
Classifier: Framework :: Django
Classifier: License :: OSI Approved :: MIT License
Classifier: Operating System :: OS Independent
License-File: LICENSE
Requires-Dist: sentry-sdk>=0.14.0
